ichec_handbook/__init__.py
ichec_handbook/content.py
ichec_handbook/hyperlink.py
ichec_handbook/link_validator.py
ichec_handbook/main_cli.py
ichec_handbook/py.typed
ichec_handbook/spellcheck.py
ichec_handbook/tags.py
ichec_handbook/document/__init__.py
ichec_handbook/document/chapter.py
ichec_handbook/document/config.py
ichec_handbook/document/part.py
ichec_handbook/document/section.py
ichec_handbook/document/toc.py
ichec_handbook/document/jupyter_book/__init__.py
ichec_handbook/document/jupyter_book/chapter.py
ichec_handbook/document/jupyter_book/part.py
ichec_handbook/document/jupyter_book/section.py
ichec_handbook/document/jupyter_book/toc.py
ichec_handbook/rendering/__init__.py
ichec_handbook/rendering/book.py
ichec_handbook/rendering/context.py
ichec_handbook/rendering/document.py
ichec_handbook/rendering/media.py
ichec_handbook/rendering/rendering.py
ichec_handbook-0.2.0.dist-info/licenses/LICENSE
ichec_handbook-0.2.0.dist-info/METADATA
ichec_handbook-0.2.0.dist-info/WHEEL
ichec_handbook-0.2.0.dist-info/entry_points.txt
ichec_handbook-0.2.0.dist-info/top_level.txt
ichec_handbook-0.2.0.dist-info/RECORD
